{
  "resources": [
    {
      "path": "data.csv",
      "name": "data",
      "profile": "tabular-data-resource",
      "scheme": "file",
      "format": "csv",
      "hashing": "md5",
      "encoding": "utf-8",
      "schema": {
        "fields": [
          {
            "name": "Year",
            "type": "integer",
            "title": "Year"
          },
          {
            "name": "GeoAreaName",
            "type": "string",
            "constraints": {
              "enum": [
                "Estonia",
                "Finland",
                "France",
                "Georgia",
                "Germany",
                "Greece",
                "Albania",
                "Azerbaijan",
                "Austria",
                "Hungary",
                "Armenia",
                "Ireland",
                "Italy",
                "Belgium",
                "Bosnia and Herzegovina",
                "Kyrgyzstan",
                "Latvia",
                "Bulgaria",
                "Belarus",
                "Lithuania",
                "Malta",
                "Croatia",
                "Republic of Moldova",
                "Cyprus",
                "Montenegro",
                "Czechia",
                "Denmark",
                "Netherlands",
                "Norway",
                "Poland",
                "Portugal",
                "Romania",
                "Serbia",
                "Slovakia",
                "Slovenia",
                "Spain",
                "Sweden",
                "Switzerland",
                "Tajikistan",
                "Türkiye",
                "Ukraine",
                "North Macedonia",
                "Uzbekistan",
                ""
              ]
            },
            "title": "GeoAreaName"
          },
          {
            "name": "Value",
            "type": "integer",
            "title": "Value"
          }
        ]
      }
    }
  ],
  "profile": "data-package",
  "name": "2-5-1_ER_GRF_PLNTSTOR",
  "title": "global_indicators.2-5-1_ER_GRF_PLNTSTOR-title"
}