{
  "resources": [
    {
      "path": "data.csv",
      "name": "data",
      "profile": "tabular-data-resource",
      "scheme": "file",
      "format": "csv",
      "hashing": "md5",
      "encoding": "utf-8",
      "schema": {
        "fields": [
          {
            "name": "Year",
            "type": "integer",
            "title": "Year"
          },
          {
            "name": "GeoAreaName",
            "type": "string",
            "constraints": {
              "enum": [
                "Republic of Moldova",
                "Azerbaijan",
                "Montenegro",
                "Armenia",
                "Serbia",
                "Bosnia and Herzegovina",
                "Tajikistan",
                "Turkmenistan",
                "Georgia",
                "North Macedonia",
                "Kazakhstan",
                "Kyrgyzstan",
                ""
              ]
            },
            "title": "GeoAreaName"
          },
          {
            "name": "Location",
            "type": "string",
            "constraints": {
              "enum": [
                "RURAL",
                "URBAN",
                "ALLAREA",
                ""
              ]
            },
            "title": "Location"
          },
          {
            "name": "Value",
            "type": "integer",
            "title": "Value"
          }
        ]
      }
    }
  ],
  "profile": "data-package",
  "name": "6-2-1_SH_SAN_HNDWSH",
  "title": "global_indicators.6-2-1_SH_SAN_HNDWSH-title"
}