{
  "resources": [
    {
      "path": "data.csv",
      "name": "data",
      "profile": "tabular-data-resource",
      "scheme": "file",
      "format": "csv",
      "hashing": "md5",
      "encoding": "utf-8",
      "schema": {
        "fields": [
          {
            "name": "Year",
            "type": "integer"
          },
          {
            "name": "GeoAreaName",
            "type": "string",
            "constraints": {
              "enum": [
                "Albania",
                "Kazakhstan",
                "Azerbaijan",
                "Austria",
                "Kyrgyzstan",
                "Armenia",
                "Latvia",
                "Lithuania",
                "Belgium",
                "Luxembourg",
                "Malta",
                "Republic of Moldova",
                "Bulgaria",
                "Belarus",
                "Denmark",
                "Estonia",
                "Netherlands",
                "Norway",
                "Finland",
                "Poland",
                "France",
                "Portugal",
                "Georgia",
                "Romania",
                "Germany",
                "Serbia",
                "Greece",
                "Hungary",
                "Ireland",
                "Italy",
                "Slovenia",
                "Spain",
                "Sweden",
                "Switzerland",
                "Türkiye",
                "North Macedonia",
                ""
              ]
            }
          },
          {
            "name": "Age",
            "type": "string",
            "constraints": {
              "enum": [
                "10+",
                "65+",
                "20-74",
                "15+",
                "15-24",
                "55-64",
                "25-44",
                "45-54",
                "12+",
                "45-64",
                "16+",
                "15-64",
                "3+",
                "20-24",
                "20-64",
                "20+",
                "10-14",
                ""
              ]
            }
          },
          {
            "name": "Location",
            "type": "string",
            "constraints": {
              "enum": [
                "RURAL",
                "URBAN",
                "ALLAREA",
                ""
              ]
            }
          },
          {
            "name": "Sex",
            "type": "string",
            "constraints": {
              "enum": [
                "MALE",
                "FEMALE",
                ""
              ]
            }
          },
          {
            "name": "Value",
            "type": "number"
          }
        ]
      }
    }
  ],
  "profile": "data-package",
  "name": "5-4-1_SL_DOM_TSPD",
  "title": "global_indicators.5-4-1_SL_DOM_TSPD-title"
}